{
    "errors": [
        "EXIT_CODE_1"
    ],
    "fails": [],
    "findings": [
        {
            "column": 1,
            "filename": "/bdata2/sc/dataset/mainnet/0xe36153288f9f536e84d0a290b614487a757ecbee.sol",
            "level": "error",
            "line": 6,
            "message": "Compiler version ^0.5.2 does not satisfy the ^0.5.8 semver requirement",
            "name": "compiler-version"
        },
        {
            "column": 9,
            "filename": "/bdata2/sc/dataset/mainnet/0xe36153288f9f536e84d0a290b614487a757ecbee.sol",
            "level": "warning",
            "line": 23,
            "message": "Error message for require is too long",
            "name": "reason-string"
        },
        {
            "column": 5,
            "filename": "/bdata2/sc/dataset/mainnet/0xe36153288f9f536e84d0a290b614487a757ecbee.sol",
            "level": "warning",
            "line": 93,
            "message": "Error message for require is too long",
            "name": "reason-string"
        },
        {
            "column": 3,
            "filename": "/bdata2/sc/dataset/mainnet/0xe36153288f9f536e84d0a290b614487a757ecbee.sol",
            "level": "warning",
            "line": 155,
            "message": "Explicitly mark visibility of state",
            "name": "state-visibility"
        },
        {
            "column": 3,
            "filename": "/bdata2/sc/dataset/mainnet/0xe36153288f9f536e84d0a290b614487a757ecbee.sol",
            "level": "warning",
            "line": 196,
            "message": "Explicitly mark visibility of state",
            "name": "state-visibility"
        },
        {
            "column": 5,
            "filename": "/bdata2/sc/dataset/mainnet/0xe36153288f9f536e84d0a290b614487a757ecbee.sol",
            "level": "warning",
            "line": 204,
            "message": "Error message for require is too long",
            "name": "reason-string"
        },
        {
            "column": 5,
            "filename": "/bdata2/sc/dataset/mainnet/0xe36153288f9f536e84d0a290b614487a757ecbee.sol",
            "level": "warning",
            "line": 225,
            "message": "Error message for require is too long",
            "name": "reason-string"
        },
        {
            "column": 5,
            "filename": "/bdata2/sc/dataset/mainnet/0xe36153288f9f536e84d0a290b614487a757ecbee.sol",
            "level": "warning",
            "line": 247,
            "message": "Error message for require is too long",
            "name": "reason-string"
        },
        {
            "column": 5,
            "filename": "/bdata2/sc/dataset/mainnet/0xe36153288f9f536e84d0a290b614487a757ecbee.sol",
            "level": "warning",
            "line": 254,
            "message": "Error message for require is too long",
            "name": "reason-string"
        },
        {
            "column": 5,
            "filename": "/bdata2/sc/dataset/mainnet/0xe36153288f9f536e84d0a290b614487a757ecbee.sol",
            "level": "warning",
            "line": 273,
            "message": "Error message for require is too long",
            "name": "reason-string"
        },
        {
            "column": 9,
            "filename": "/bdata2/sc/dataset/mainnet/0xe36153288f9f536e84d0a290b614487a757ecbee.sol",
            "level": "warning",
            "line": 307,
            "message": "Error message for require is too long",
            "name": "reason-string"
        }
    ],
    "infos": [],
    "parser": {
        "id": "solhint-3.3.8",
        "mode": "solidity",
        "version": "2023/02/12"
    }
}
