{
    "errors": [],
    "fails": [],
    "findings": [
        {
            "address": 4716,
            "filename": "/bdata2/sc/dataset/mainnet_bytecode/0x89816B6412dC9d216e1E7428279123b1f4973f1E.rt.hex",
            "name": "ReentrantCall"
        },
        {
            "address": 4716,
            "filename": "/bdata2/sc/dataset/mainnet_bytecode/0x89816B6412dC9d216e1E7428279123b1f4973f1E.rt.hex",
            "name": "UncheckedCall"
        }
    ],
    "infos": [
        "Warning: Deprecated type declaration"
    ],
    "parser": {
        "id": "vandal",
        "mode": "runtime",
        "version": "2023/02/27"
    }
}
