{
    "errors": [
        "EXIT_CODE_1"
    ],
    "fails": [],
    "findings": [
        {
            "column": 1,
            "filename": "/bdata2/sc/dataset/mainnet/0x19C23A427d382769040e402ff6D3A48240153A8a.sol",
            "level": "error",
            "line": 6,
            "message": "Compiler version ^0.7.0 does not satisfy the ^0.5.8 semver requirement",
            "name": "compiler-version"
        },
        {
            "column": 1,
            "filename": "/bdata2/sc/dataset/mainnet/0x19C23A427d382769040e402ff6D3A48240153A8a.sol",
            "level": "error",
            "line": 84,
            "message": "Compiler version 0.7.6 does not satisfy the ^0.5.8 semver requirement",
            "name": "compiler-version"
        },
        {
            "column": 1,
            "filename": "/bdata2/sc/dataset/mainnet/0x19C23A427d382769040e402ff6D3A48240153A8a.sol",
            "level": "error",
            "line": 95,
            "message": "Compiler version >=0.6.0 <0.8.0 does not satisfy the ^0.5.8 semver requirement",
            "name": "compiler-version"
        },
        {
            "column": 1,
            "filename": "/bdata2/sc/dataset/mainnet/0x19C23A427d382769040e402ff6D3A48240153A8a.sol",
            "level": "error",
            "line": 119,
            "message": "Compiler version 0.7.6 does not satisfy the ^0.5.8 semver requirement",
            "name": "compiler-version"
        },
        {
            "column": 5,
            "filename": "/bdata2/sc/dataset/mainnet/0x19C23A427d382769040e402ff6D3A48240153A8a.sol",
            "level": "warning",
            "line": 139,
            "message": "Explicitly mark visibility in function (Set ignoreConstructors to true if using solidity >=0.7.0)",
            "name": "func-visibility"
        },
        {
            "column": 17,
            "filename": "/bdata2/sc/dataset/mainnet/0x19C23A427d382769040e402ff6D3A48240153A8a.sol",
            "level": "warning",
            "line": 162,
            "message": "Avoid making time-based decisions in your business logic",
            "name": "not-rely-on-time"
        },
        {
            "column": 1,
            "filename": "/bdata2/sc/dataset/mainnet/0x19C23A427d382769040e402ff6D3A48240153A8a.sol",
            "level": "error",
            "line": 169,
            "message": "Compiler version ^0.7.0 does not satisfy the ^0.5.8 semver requirement",
            "name": "compiler-version"
        },
        {
            "column": 9,
            "filename": "/bdata2/sc/dataset/mainnet/0x19C23A427d382769040e402ff6D3A48240153A8a.sol",
            "level": "warning",
            "line": 285,
            "message": "Error message for require is too long",
            "name": "reason-string"
        },
        {
            "column": 1,
            "filename": "/bdata2/sc/dataset/mainnet/0x19C23A427d382769040e402ff6D3A48240153A8a.sol",
            "level": "error",
            "line": 384,
            "message": "Compiler version ^0.7.0 does not satisfy the ^0.5.8 semver requirement",
            "name": "compiler-version"
        },
        {
            "column": 5,
            "filename": "/bdata2/sc/dataset/mainnet/0x19C23A427d382769040e402ff6D3A48240153A8a.sol",
            "level": "warning",
            "line": 436,
            "message": "Explicitly mark visibility in function (Set ignoreConstructors to true if using solidity >=0.7.0)",
            "name": "func-visibility"
        },
        {
            "column": 9,
            "filename": "/bdata2/sc/dataset/mainnet/0x19C23A427d382769040e402ff6D3A48240153A8a.sol",
            "level": "warning",
            "line": 590,
            "message": "Error message for require is too long",
            "name": "reason-string"
        },
        {
            "column": 9,
            "filename": "/bdata2/sc/dataset/mainnet/0x19C23A427d382769040e402ff6D3A48240153A8a.sol",
            "level": "warning",
            "line": 591,
            "message": "Error message for require is too long",
            "name": "reason-string"
        },
        {
            "column": 9,
            "filename": "/bdata2/sc/dataset/mainnet/0x19C23A427d382769040e402ff6D3A48240153A8a.sol",
            "level": "warning",
            "line": 631,
            "message": "Error message for require is too long",
            "name": "reason-string"
        },
        {
            "column": 9,
            "filename": "/bdata2/sc/dataset/mainnet/0x19C23A427d382769040e402ff6D3A48240153A8a.sol",
            "level": "warning",
            "line": 654,
            "message": "Error message for require is too long",
            "name": "reason-string"
        },
        {
            "column": 9,
            "filename": "/bdata2/sc/dataset/mainnet/0x19C23A427d382769040e402ff6D3A48240153A8a.sol",
            "level": "warning",
            "line": 655,
            "message": "Error message for require is too long",
            "name": "reason-string"
        },
        {
            "column": 94,
            "filename": "/bdata2/sc/dataset/mainnet/0x19C23A427d382769040e402ff6D3A48240153A8a.sol",
            "level": "warning",
            "line": 686,
            "message": "Code contains empty blocks",
            "name": "no-empty-blocks"
        },
        {
            "column": 1,
            "filename": "/bdata2/sc/dataset/mainnet/0x19C23A427d382769040e402ff6D3A48240153A8a.sol",
            "level": "error",
            "line": 691,
            "message": "Compiler version ^0.7.6 does not satisfy the ^0.5.8 semver requirement",
            "name": "compiler-version"
        },
        {
            "column": 1,
            "filename": "/bdata2/sc/dataset/mainnet/0x19C23A427d382769040e402ff6D3A48240153A8a.sol",
            "level": "error",
            "line": 699,
            "message": "Compiler version ^0.7.6 does not satisfy the ^0.5.8 semver requirement",
            "name": "compiler-version"
        },
        {
            "column": 1,
            "filename": "/bdata2/sc/dataset/mainnet/0x19C23A427d382769040e402ff6D3A48240153A8a.sol",
            "level": "error",
            "line": 707,
            "message": "Compiler version ^0.7.6 does not satisfy the ^0.5.8 semver requirement",
            "name": "compiler-version"
        }
    ],
    "infos": [],
    "parser": {
        "id": "solhint-3.3.8",
        "mode": "solidity",
        "version": "2023/02/12"
    }
}
