{
    "errors": [
        "SYMBOLIC EXECUTION TIMEOUT"
    ],
    "fails": [],
    "findings": [
        {
            "column": 30,
            "contract": "FOMO3",
            "filename": "/bdata2/sc/dataset/mainnet/0xd63a8be8e56dbb1a164d21cbb58331a0546b5a9a.sol",
            "line": 1569,
            "name": "Overflow bugs"
        },
        {
            "column": 29,
            "contract": "FOMO3",
            "filename": "/bdata2/sc/dataset/mainnet/0xd63a8be8e56dbb1a164d21cbb58331a0546b5a9a.sol",
            "line": 1570,
            "name": "Overflow bugs"
        },
        {
            "column": 47,
            "contract": "FOMO3",
            "filename": "/bdata2/sc/dataset/mainnet/0xd63a8be8e56dbb1a164d21cbb58331a0546b5a9a.sol",
            "line": 619,
            "name": "Reentrancy bug"
        },
        {
            "column": 30,
            "contract": "FOMO3",
            "filename": "/bdata2/sc/dataset/mainnet/0xd63a8be8e56dbb1a164d21cbb58331a0546b5a9a.sol",
            "line": 1569,
            "name": "Underflow bugs"
        }
    ],
    "infos": [],
    "parser": {
        "id": "osiris",
        "mode": "solidity",
        "version": "2023/02/27"
    }
}
